dynode/__init__.py
dynode/containers.py
dynode/recorder.py
dynode/simulation.py
dynode/system.py
dynode-0.4.0.dist-info/LICENSE
dynode-0.4.0.dist-info/METADATA
dynode-0.4.0.dist-info/WHEEL
dynode-0.4.0.dist-info/top_level.txt
dynode-0.4.0.dist-info/RECORD
