Metadata-Version: 2.1
Name: dynode
Version: 0.4.0
Summary: A framework for modelling and simulation of dynamical systems
Home-page: https://github.com/freol35241/dynode
Author: Fredrik Olsson
Author-email: freol@outlook.com
Maintainer: Fredrik Olsson
Maintainer-email: freol@outlook.com
License: MIT
Platform: UNKNOWN
Classifier: Development Status :: 4 - Beta
Classifier: Programming Language :: Python :: 3.6
Classifier: Programming Language :: Python :: 3.7
Classifier: Programming Language :: Python :: 3.8
Classifier: Operating System :: OS Independent
Classifier: License :: OSI Approved :: MIT License
Requires-Python: >=3.6
Requires-Dist: numpy
Requires-Dist: scipy
Requires-Dist: graphlib-backport ; python_version < "3.9"
